giverny/__init__.py
giverny/turbulence_dataset.py
giverny/turbulence_gizmos/__init__.py
giverny/turbulence_gizmos/basic_gizmos.py
giverny/turbulence_gizmos/constants.py
giverny/turbulence_gizmos/getBladeData.py
giverny/turbulence_gizmos/getCutout.py
giverny/turbulence_gizmos/getData.py
giverny/turbulence_gizmos/getTurbineData.py
giverny/turbulence_gizmos/jhtdb_schema.py
giverny/turbulence_gizmos/variable_dy_grid_ys.py
giverny/turbulence_gizmos/variable_grids.py
giverny/turbulence_toolkit.py
giverny-3.5.2.dist-info/METADATA
giverny-3.5.2.dist-info/WHEEL
giverny-3.5.2.dist-info/licenses/LICENSE.txt
giverny-3.5.2.dist-info/RECORD
