Metadata-Version: 2.4
Name: giverny
Version: 3.5.2
Summary: library to query the Johns Hopkins Turbulence Database (JHTDB)
License-Expression: Apache-2.0
License-File: LICENSE.txt
Author: Johns Hopkins Turbulence Database Group
Requires-Python: >=3.9,<4.0
Classifier: Development Status :: 5 - Production/Stable
Classifier: Intended Audience :: Science/Research
Classifier: Topic :: Scientific/Engineering :: Atmospheric Science
Classifier: Topic :: Scientific/Engineering :: Physics
Requires-Dist: attrs (>=23.2.0,<26.0.0)
Requires-Dist: bokeh (>=2.4.3,<4.0.0)
Requires-Dist: dill (>=0.3.6,<1.0.0)
Requires-Dist: duckdb (>=1.2.2,<2.0.0)
Requires-Dist: h5py (>=3.7.0,<4.0.0)
Requires-Dist: jsonschema (>=4.23.0,<5.0.0)
Requires-Dist: jsonschema-specifications (>=2023.12.1,<2024.11.0)
Requires-Dist: jupyter-core (>=5.7.2,<6.0.0)
Requires-Dist: matplotlib (>=3.6.2,<4.0.0)
Requires-Dist: nbformat (>=5.10.4,<6.0.0)
Requires-Dist: netcdf4 (>=1.6.1,<2.0.0)
Requires-Dist: numpy (>=1.23.4,<3.0.0)
Requires-Dist: pandas (>=1.5.1,<3.0.0)
Requires-Dist: plotly (>=5.11.0,<7.0.0)
Requires-Dist: pyarrow (>=19.0.1,<20.0.0)
Requires-Dist: pydantic (>=2.10.6,<3.0.0)
Requires-Dist: referencing (>=0.35.1,<1.0.0)
Requires-Dist: requests (>=2.31.0,<3.0.0)
Requires-Dist: rpds-py (>=0.19.1,<1.0.0)
Requires-Dist: scipy (>=1.9.3,<2.0.0)
Requires-Dist: sympy (>=1.12,<2.0.0)
Requires-Dist: tqdm (>=4.64.1,<5.0.0)
Requires-Dist: wurlitzer (>=3.0.3,<4.0.0)
Requires-Dist: xarray (>=2022.11.0,<2025.4.0)
Requires-Dist: zarr (>=2.13.3,<4.0.0)
Project-URL: Bug Tracker, https://github.com/sciserver/giverny/issues
Project-URL: Changelog, https://github.com/sciserver/giverny/blob/main/CHANGELOG.md
Project-URL: Homepage, https://github.com/sciserver/giverny
